topsis/__init__.py
topsis/topsis.py
topsis_Shivansh_102203508-1.0.1.dist-info/LICENSE
topsis_Shivansh_102203508-1.0.1.dist-info/METADATA
topsis_Shivansh_102203508-1.0.1.dist-info/WHEEL
topsis_Shivansh_102203508-1.0.1.dist-info/entry_points.txt
topsis_Shivansh_102203508-1.0.1.dist-info/top_level.txt
topsis_Shivansh_102203508-1.0.1.dist-info/RECORD
