Metadata-Version: 2.1
Name: topsis-Shivansh-102203508
Version: 1.0.1
Summary: A Python package for performing TOPSIS analysis.
Home-page: https://github.com/shivanshg29/Topsis
Author: Shivansh Gupta
Author-email: shivanshgupta290804@gmail.com
Requires-Python: >=3.6
License-File: LICENSE
Requires-Dist: pandas>=1.0.0
